<?xml version="1.0" encoding="utf-8" ?><dwsync><file name="gift.svg" server="03cf57b.netsolhost.com//htdocs/" local="3550656041" remote="319783739194535548" Dst="-1" /><file name="people.svg" server="03cf57b.netsolhost.com//htdocs/" local="3550656092" remote="319783739194535548" Dst="-1" /><file name="trophy.svg" server="03cf57b.netsolhost.com//htdocs/" local="3550656064" remote="319783739194535548" Dst="-1" /><file name="heart.svg" server="03cf57b.netsolhost.com//htdocs/" local="3550656052" remote="319783739194535548" Dst="-1" /><file name="lightbulb.svg" server="03cf57b.netsolhost.com//htdocs/" local="3550656079" remote="319783739194535548" Dst="-1" /><file name="gift-white.svg" server="03cf57b.netsolhost.com//htdocs/" local="3551288520" remote="319783739195153608" Dst="-1" /><file name="trophy-white.svg" server="03cf57b.netsolhost.com//htdocs/" local="3551293440" remote="319783739195158528" Dst="-1" /><file name="lightbulb-white.svg" server="03cf57b.netsolhost.com//htdocs/" local="3551288520" remote="319783739195153608" Dst="-1" /><file name="people-white-bg.svg" server="03cf57b.netsolhost.com//htdocs/" local="3551288520" remote="319783739195153608" Dst="-1" /><file name="ribbon-white.svg" server="03cf57b.netsolhost.com//htdocs/" local="3551288520" remote="319783739195153608" Dst="-1" /><file name="heart-white.svg" server="03cf57b.netsolhost.com//htdocs/" local="3551288520" remote="319783739195153608" Dst="-1" /></dwsync>